det_cli/__init__.py
det_cli/__main__.py
det_cli/protocol_handler.py
det_cli/register.py
det_cli-0.1.4.dist-info/METADATA
det_cli-0.1.4.dist-info/WHEEL
det_cli-0.1.4.dist-info/entry_points.txt
det_cli-0.1.4.dist-info/top_level.txt
det_cli-0.1.4.dist-info/RECORD
